cerevox/__init__.py
cerevox/apis/__init__.py
cerevox/apis/account.py
cerevox/apis/async_account.py
cerevox/apis/async_hippo.py
cerevox/apis/async_lexa.py
cerevox/apis/hippo.py
cerevox/apis/lexa.py
cerevox/core/__init__.py
cerevox/core/async_client.py
cerevox/core/client.py
cerevox/core/constants.py
cerevox/core/exceptions.py
cerevox/core/models.py
cerevox/services/__init__.py
cerevox/services/async_ingest.py
cerevox/services/ingest.py
cerevox/utils/__init__.py
cerevox/utils/document_loader.py
cerevox-0.2.0.dist-info/licenses/LICENSE
cerevox-0.2.0.dist-info/METADATA
cerevox-0.2.0.dist-info/WHEEL
cerevox-0.2.0.dist-info/top_level.txt
cerevox-0.2.0.dist-info/RECORD
