Metadata-Version: 2.4
Name: cerevox
Version: 0.2.0
Summary: Official Python SDK for Cerevox - The Data Layer for AI Agents: data parsing (Lexa) and data search (Hippo)
Author-email: Cerevox <support@cerevox.ai>, Muaz Siddiqui <muaz@cerevox.ai>
License-Expression: MIT
Project-URL: Homepage, https://cerevox.ai
Project-URL: Documentation, https://docs.cerevox.ai
Project-URL: Repository, https://github.com/CerevoxAI/cerevox-python
Project-URL: Bug Tracker, https://github.com/CerevoxAI/cerevox-python/issues
Project-URL: API Reference, https://data.cerevox.ai/docs
Keywords: ai-agents,data-layer,document-parsing,semantic-search,data-search,api,pdf,extraction,async,vector-database,chunking,rag,retrieval,qa,ai
Classifier: Development Status :: 4 - Beta
Classifier: Intended Audience :: Developers
Classifier: Operating System :: OS Independent
Classifier: Programming Language :: Python :: 3
Classifier: Programming Language :: Python :: 3.9
Classifier: Programming Language :: Python :: 3.10
Classifier: Programming Language :: Python :: 3.11
Classifier: Programming Language :: Python :: 3.12
Classifier: Programming Language :: Python :: 3.13
Classifier: Topic :: Software Development :: Libraries :: Python Modules
Classifier: Topic :: Text Processing
Classifier: Topic :: Scientific/Engineering :: Information Analysis
Requires-Python: >=3.9
License-File: LICENSE
Requires-Dist: aiohttp>=3.12.4
Requires-Dist: aiofiles>=24.1.0
Requires-Dist: requests>=2.32.3
Requires-Dist: urllib3>=2.4.0
Requires-Dist: pydantic>=2.11.5
Provides-Extra: data
Requires-Dist: pandas>=2.3.0; extra == "data"
Requires-Dist: beautifulsoup4>=4.13.4; extra == "data"
Requires-Dist: tqdm>=4.66.0; extra == "data"
Provides-Extra: dev
Requires-Dist: pytest>=8.3.5; extra == "dev"
Requires-Dist: pytest-asyncio>=0.23.0; extra == "dev"
Requires-Dist: pytest-cov>=4.0.0; extra == "dev"
Requires-Dist: pytest-timeout>=2.1.0; extra == "dev"
Requires-Dist: aioresponses>=0.7.8; extra == "dev"
Requires-Dist: responses>=0.25.7; extra == "dev"
Requires-Dist: black>=24.0.0; extra == "dev"
Requires-Dist: isort>=5.0.0; extra == "dev"
Requires-Dist: mypy>=1.0.0; extra == "dev"
Requires-Dist: types-Pygments; extra == "dev"
Requires-Dist: types-beautifulsoup4; extra == "dev"
Requires-Dist: types-requests; extra == "dev"
Requires-Dist: types-tqdm; extra == "dev"
Requires-Dist: safety>=3.0.0; extra == "dev"
Requires-Dist: bandit[toml]>=1.7.0; extra == "dev"
Provides-Extra: all
Requires-Dist: pandas>=2.3.0; extra == "all"
Requires-Dist: beautifulsoup4>=4.13.4; extra == "all"
Requires-Dist: tqdm>=4.66.0; extra == "all"
Requires-Dist: pytest>=8.3.5; extra == "all"
Requires-Dist: pytest-asyncio>=0.23.0; extra == "all"
Requires-Dist: pytest-cov>=4.0.0; extra == "all"
Requires-Dist: pytest-timeout>=2.1.0; extra == "all"
Requires-Dist: aioresponses>=0.7.8; extra == "all"
Requires-Dist: responses>=0.25.7; extra == "all"
Requires-Dist: black>=24.0.0; extra == "all"
Requires-Dist: isort>=5.0.0; extra == "all"
Requires-Dist: mypy>=1.0.0; extra == "all"
Requires-Dist: types-Pygments; extra == "all"
Requires-Dist: types-beautifulsoup4; extra == "all"
Requires-Dist: types-requests; extra == "all"
Requires-Dist: types-tqdm; extra == "all"
Requires-Dist: safety>=3.0.0; extra == "all"
Requires-Dist: bandit[toml]>=1.7.0; extra == "all"
Dynamic: license-file
